pymdownx/__init__.py
pymdownx/__meta__.py
pymdownx/_bypassnorm.py
pymdownx/arithmatex.py
pymdownx/b64.py
pymdownx/betterem.py
pymdownx/caret.py
pymdownx/critic.py
pymdownx/details.py
pymdownx/emoji.py
pymdownx/emoji1_db.py
pymdownx/escapeall.py
pymdownx/extra.py
pymdownx/fancylists.py
pymdownx/gemoji_db.py
pymdownx/highlight.py
pymdownx/inlinehilite.py
pymdownx/keymap_db.py
pymdownx/keys.py
pymdownx/magiclink.py
pymdownx/mark.py
pymdownx/pathconverter.py
pymdownx/progressbar.py
pymdownx/saneheaders.py
pymdownx/slugs.py
pymdownx/smartsymbols.py
pymdownx/snippets.py
pymdownx/striphtml.py
pymdownx/superfences.py
pymdownx/tabbed.py
pymdownx/tasklist.py
pymdownx/tilde.py
pymdownx/twemoji_db.py
pymdownx/util.py
pymdownx/blocks/__init__.py
pymdownx/blocks/admonition.py
pymdownx/blocks/block.py
pymdownx/blocks/caption.py
pymdownx/blocks/definition.py
pymdownx/blocks/details.py
pymdownx/blocks/html.py
pymdownx/blocks/tab.py
pymdown_extensions-10.17.dist-info/METADATA
pymdown_extensions-10.17.dist-info/WHEEL
pymdown_extensions-10.17.dist-info/licenses/LICENSE.md
pymdown_extensions-10.17.dist-info/RECORD
